mediaToolsUtils/SoundCollection.py
mediaToolsUtils/VideoCapture.py
mediaToolsUtils/__init__.py
mediaToolsUtils/__main__.py
mediaToolsUtils-1.0.0.dist-info/LICENSE
mediaToolsUtils-1.0.0.dist-info/METADATA
mediaToolsUtils-1.0.0.dist-info/WHEEL
mediaToolsUtils-1.0.0.dist-info/top_level.txt
mediaToolsUtils-1.0.0.dist-info/RECORD
